gnosis_track/__init__.py
gnosis_track/cli/__init__.py
gnosis_track/cli/install.py
gnosis_track/cli/logs.py
gnosis_track/cli/main.py
gnosis_track/cli/manage.py
gnosis_track/core/__init__.py
gnosis_track/core/auth_manager.py
gnosis_track/core/bucket_manager.py
gnosis_track/core/config_manager.py
gnosis_track/core/seaweed_client.py
gnosis_track/core/token_manager.py
gnosis_track/logging/__init__.py
gnosis_track/logging/log_formatter.py
gnosis_track/logging/log_streamer.py
gnosis_track/logging/validator_logger.py
gnosis_track/ui/__init__.py
gnosis_track/ui/server.py
gnosis_track/ui/static/app.js
gnosis_track/ui/templates/error.html
gnosis_track/ui/templates/index.html
gnosis_track/ui/templates/login.html
gnosis_track-0.1.1.dist-info/licenses/LICENSE
gnosis_track-0.1.1.dist-info/METADATA
gnosis_track-0.1.1.dist-info/WHEEL
gnosis_track-0.1.1.dist-info/entry_points.txt
gnosis_track-0.1.1.dist-info/top_level.txt
gnosis_track-0.1.1.dist-info/RECORD
