Metadata-Version: 2.4
Name: gnosis-track
Version: 0.1.1
Summary: Secure distributed object storage and logging with SeaweedFS
Home-page: https://github.com/gnosis-research/gnosis-track
Author: Gnosis Research
Author-email: Volodymyr Truba <trubavolodymyr@gmail.com>
Maintainer-email: Volodymyr Truba <trubavolodymyr@gmail.com>
License: MIT License
Project-URL: Homepage, https://github.com/gnosis-research/gnosis-track
Project-URL: Documentation, https://github.com/gnosis-research/gnosis-track#readme
Project-URL: Repository, https://github.com/gnosis-research/gnosis-track.git
Project-URL: Issues, https://github.com/gnosis-research/gnosis-track/issues
Keywords: seaweedfs,object-storage,logging,distributed,s3
Classifier: Development Status :: 3 - Alpha
Classifier: Intended Audience :: Developers
Classifier: License :: OSI Approved :: MIT License
Classifier: Operating System :: OS Independent
Classifier: Programming Language :: Python :: 3
Classifier: Programming Language :: Python :: 3.8
Classifier: Programming Language :: Python :: 3.9
Classifier: Programming Language :: Python :: 3.10
Classifier: Programming Language :: Python :: 3.11
Classifier: Programming Language :: Python :: 3.12
Classifier: Topic :: System :: Distributed Computing
Classifier: Topic :: System :: Logging
Classifier: Topic :: System :: Systems Administration
Requires-Python: >=3.8
License-File: LICENSE
Requires-Dist: boto3>=1.34.0
Requires-Dist: botocore>=1.34.0
Requires-Dist: requests>=2.31.0
Requires-Dist: pyyaml>=6.0.1
Requires-Dist: click>=8.1.0
Requires-Dist: pydantic>=2.5.0
Requires-Dist: cryptography>=41.0.0
Requires-Dist: PyJWT>=2.10.0
Requires-Dist: python-dotenv>=1.0.0
Requires-Dist: jsonschema>=4.20.0
Requires-Dist: setuptools>=68.0
Provides-Extra: dev
Requires-Dist: pytest>=7.0.0; extra == "dev"
Requires-Dist: pytest-asyncio>=0.21.0; extra == "dev"
Requires-Dist: pytest-cov>=4.0.0; extra == "dev"
Requires-Dist: black>=23.0.0; extra == "dev"
Requires-Dist: isort>=5.12.0; extra == "dev"
Requires-Dist: flake8>=6.0.0; extra == "dev"
Requires-Dist: mypy>=1.0.0; extra == "dev"
Provides-Extra: ui
Requires-Dist: fastapi>=0.104.0; extra == "ui"
Requires-Dist: uvicorn[standard]>=0.24.0; extra == "ui"
Requires-Dist: jinja2>=3.1.0; extra == "ui"
Provides-Extra: monitoring
Requires-Dist: prometheus-client>=0.18.0; extra == "monitoring"
Requires-Dist: grafana-api>=1.0.3; extra == "monitoring"
Dynamic: author
Dynamic: home-page
Dynamic: license-file
Dynamic: requires-python
